__init__.py
tempesta_excel.py
tempesta_excel-2.0.dist-info/LICENSE
tempesta_excel-2.0.dist-info/METADATA
tempesta_excel-2.0.dist-info/WHEEL
tempesta_excel-2.0.dist-info/top_level.txt
tempesta_excel-2.0.dist-info/RECORD
