Metadata-Version: 2.1
Name: tempesta-excel
Version: 2.0
Summary: A small package to manipulate Excel files
Author-email: Jose Tempesta <zetempesta@gmail.com>
Project-URL: Homepage, https://github.com/zetempesta/excel
Classifier: Programming Language :: Python :: 3
Classifier: License :: OSI Approved :: MIT License
Classifier: Operating System :: OS Independent
Requires-Python: >=3.10
License-File: LICENSE
